alibabacloud_eiam20211201/__init__.py
alibabacloud_eiam20211201/client.py
alibabacloud_eiam20211201/models/__init__.py
alibabacloud_eiam20211201/models/_add_application_account_to_user_request.py
alibabacloud_eiam20211201/models/_add_application_account_to_user_response.py
alibabacloud_eiam20211201/models/_add_application_account_to_user_response_body.py
alibabacloud_eiam20211201/models/_add_custom_privacy_policies_to_brand_request.py
alibabacloud_eiam20211201/models/_add_custom_privacy_policies_to_brand_response.py
alibabacloud_eiam20211201/models/_add_custom_privacy_policies_to_brand_response_body.py
alibabacloud_eiam20211201/models/_add_user_to_organizational_units_request.py
alibabacloud_eiam20211201/models/_add_user_to_organizational_units_response.py
alibabacloud_eiam20211201/models/_add_user_to_organizational_units_response_body.py
alibabacloud_eiam20211201/models/_add_users_to_group_request.py
alibabacloud_eiam20211201/models/_add_users_to_group_response.py
alibabacloud_eiam20211201/models/_add_users_to_group_response_body.py
alibabacloud_eiam20211201/models/_authorize_application_to_groups_request.py
alibabacloud_eiam20211201/models/_authorize_application_to_groups_response.py
alibabacloud_eiam20211201/models/_authorize_application_to_groups_response_body.py
alibabacloud_eiam20211201/models/_authorize_application_to_organizational_units_request.py
alibabacloud_eiam20211201/models/_authorize_application_to_organizational_units_response.py
alibabacloud_eiam20211201/models/_authorize_application_to_organizational_units_response_body.py
alibabacloud_eiam20211201/models/_authorize_application_to_users_request.py
alibabacloud_eiam20211201/models/_authorize_application_to_users_response.py
alibabacloud_eiam20211201/models/_authorize_application_to_users_response_body.py
alibabacloud_eiam20211201/models/_authorize_resource_server_scopes_to_client_request.py
alibabacloud_eiam20211201/models/_authorize_resource_server_scopes_to_client_response.py
alibabacloud_eiam20211201-2.9.0.dist-info/LICENSE
alibabacloud_eiam20211201-2.9.0.dist-info/METADATA
alibabacloud_eiam20211201-2.9.0.dist-info/WHEEL
alibabacloud_eiam20211201-2.9.0.dist-info/top_level.txt
alibabacloud_eiam20211201-2.9.0.dist-info/RECORD
